CHANGELOG.md
majormode/__init__.py
majormode/perseus/__init__.py
majormode/perseus/agent/__init__.py
majormode/perseus/agent/base.py
perseus_agent_library-1.0.13.dist-info/LICENSE.md
perseus_agent_library-1.0.13.dist-info/WHEEL
perseus_agent_library-1.0.13.dist-info/METADATA
perseus_agent_library-1.0.13.dist-info/RECORD
