Metadata-Version: 2.1
Name: perseus-agent-library
Version: 1.0.13
Summary: Perseus Agent Python Library
Home-page: https://github.com/majormode/perseus-agent-python-library
License: SEE LICENSE IN <LICENSE.md>
Keywords: core,library,perseus
Author: Daniel CAUNE
Author-email: daniel.caune@gmail.com
Requires-Python: >=3.9,<4.0
Classifier: Development Status :: 5 - Production/Stable
Classifier: License :: Other/Proprietary License
Classifier: Operating System :: OS Independent
Classifier: Programming Language :: Python
Classifier: Programming Language :: Python :: 3
Classifier: Programming Language :: Python :: 3.9
Classifier: Programming Language :: Python :: 3.10
Classifier: Programming Language :: Python :: 3.11
Classifier: Topic :: Software Development :: Libraries
Requires-Dist: perseus-core-library (>=1.19,<2.0)
Requires-Dist: perseus-getenv-library (>=1.0,<2.0)
Requires-Dist: perseus-microrm-library (>=1.3,<2.0)
Project-URL: Repository, https://github.com/majormode/perseus-agent-python-library
